bandbox/__init__.py
bandbox/cli.py
bandbox/core.py
bandbox/engines.py
bandbox/main.py
bandbox/managers.py
bandbox/models.py
bandbox/tests.py
bandbox/utils.py
bandbox-0.2.2.dist-info/LICENSE
bandbox-0.2.2.dist-info/METADATA
bandbox-0.2.2.dist-info/WHEEL
bandbox-0.2.2.dist-info/entry_points.txt
bandbox-0.2.2.dist-info/top_level.txt
bandbox-0.2.2.dist-info/RECORD
